LICENSE
MANIFEST.in
README.rst
setup.py
django_chartbuilder/__init__.py
django_chartbuilder/__init__.pyc
django_chartbuilder/models.py
django_chartbuilder/models.pyc
django_chartbuilder/tests.py
django_chartbuilder/urls.py
django_chartbuilder/urls.pyc
django_chartbuilder/views.py
django_chartbuilder/views.pyc
django_chartbuilder.egg-info/PKG-INFO
django_chartbuilder.egg-info/SOURCES.txt
django_chartbuilder.egg-info/dependency_links.txt
django_chartbuilder.egg-info/top_level.txt
django_chartbuilder/static/django_chartbuilder/Chartbuilder/.htaccess
django_chartbuilder/static/django_chartbuilder/Chartbuilder/Getting_Started.md
django_chartbuilder/static/django_chartbuilder/Chartbuilder/LICENSE
django_chartbuilder/static/django_chartbuilder/Chartbuilder/README.md
django_chartbuilder/static/django_chartbuilder/Chartbuilder/bower.json
django_chartbuilder/static/django_chartbuilder/Chartbuilder/index.html
django_chartbuilder/static/django_chartbuilder/Chartbuilder/bower_components/canvg/.bower.json
django_chartbuilder/static/django_chartbuilder/Chartbuilder/bower_components/canvg/MIT-LICENSE.txt
django_chartbuilder/static/django_chartbuilder/Chartbuilder/bower_components/canvg/StackBlur.js
django_chartbuilder/static/django_chartbuilder/Chartbuilder/bower_components/canvg/canvg.js
django_chartbuilder/static/django_chartbuilder/Chartbuilder/bower_components/canvg/rgbcolor.js
django_chartbuilder/static/django_chartbuilder/Chartbuilder/bower_components/d3/.bower.json
django_chartbuilder/static/django_chartbuilder/Chartbuilder/bower_components/d3/.gitignore
django_chartbuilder/static/django_chartbuilder/Chartbuilder/bower_components/d3/.gitmodules
django_chartbuilder/static/django_chartbuilder/Chartbuilder/bower_components/d3/.npmignore
django_chartbuilder/static/django_chartbuilder/Chartbuilder/bower_components/d3/LICENSE
django_chartbuilder/static/django_chartbuilder/Chartbuilder/bower_components/d3/Makefile
django_chartbuilder/static/django_chartbuilder/Chartbuilder/bower_components/d3/README.md
django_chartbuilder/static/django_chartbuilder/Chartbuilder/bower_components/d3/component.json
